pi_blink/__init__.py
pi_blink/blink.py
pi_blink/blinker/base.py
pi_blink/events.py
pi_blink/ordered_set.py
pi_blink/utils/id_utils.py
pi_blink-1.0.3.dist-info/METADATA
pi_blink-1.0.3.dist-info/WHEEL
pi_blink-1.0.3.dist-info/RECORD
