Metadata-Version: 2.1
Name: pi-blink
Version: 1.0.3
Summary: Simple event library built on top of Blinker
Author: leeparnell
Author-email: 152523161+leeparnell@users.noreply.github.com
Requires-Python: >=3.10,<4.0
Classifier: Programming Language :: Python :: 3
Classifier: Programming Language :: Python :: 3.10
Classifier: Programming Language :: Python :: 3.11
Classifier: Programming Language :: Python :: 3.12
Requires-Dist: blinker (>=1.8.2,<2.0.0)
Requires-Dist: pydantic (>=2.7.3,<3.0.0)
